sharp_darwin/SharpDarwin.py
sharp_darwin/__init__.py
sharp_darwin/exceptions.py
sharp_darwin/frontend.py
sharp_darwin/sharp_darwin_cli.py
sharp_darwin/utils.py
sharp_darwin-1.3.7.dist-info/METADATA
sharp_darwin-1.3.7.dist-info/WHEEL
sharp_darwin-1.3.7.dist-info/entry_points.txt
sharp_darwin-1.3.7.dist-info/top_level.txt
sharp_darwin-1.3.7.dist-info/RECORD
