Metadata-Version: 2.1
Name: sharp-darwin
Version: 1.3.7
Summary: Spotify Playlist Manager
Home-page: https://github.com/rmrfslashbin/sharp-darwin
Author: Robert Sigler
Author-email: sigler@improvisedscience.org
License: UNKNOWN
Platform: UNKNOWN
Classifier: Programming Language :: Python :: 3
Classifier: License :: OSI Approved :: MIT License
Classifier: Operating System :: OS Independent
Requires-Python: >=3.6
Requires-Dist: spotipy (>=2.10)
Requires-Dist: python-dotenv (>=0.12)
Requires-Dist: argcomplete (>=1.11)
